README.md
setup.py
cache_page_per_user/__init__.py
cache_page_per_user/cache.py
cache_page_per_user/constants.py
cache_page_per_user/utils.py
django_cache_page_per_user.egg-info/PKG-INFO
django_cache_page_per_user.egg-info/SOURCES.txt
django_cache_page_per_user.egg-info/dependency_links.txt
django_cache_page_per_user.egg-info/top_level.txt
tests/__init__.py
tests/settings.py
tests/test.py
tests/posts/__init__.py
tests/posts/constants.py
tests/posts/factories.py
tests/posts/models.py
tests/posts/serializers.py
tests/posts/urls.py
tests/posts/views.py