Metadata-Version: 2.1
Name: django-cache-page-per-user
Version: 0.1.0
Summary: decorator for view caching per user and per language
Home-page: https://github.com/chessmaster04/django-cache-page-per-user
Author: Boris Trubin
Author-email: mgbit3214@gmail.com
License: UNKNOWN
Keywords: Django,Django Cache,cache_page,Django Cache Page Per User,Django Cache Page Per Language,Django Cache View Per User
Platform: UNKNOWN
Classifier: Development Status :: 5 - Production/Stable
Classifier: Environment :: Web Environment
Classifier: Framework :: Django
Classifier: Programming Language :: Python :: 3
Classifier: Intended Audience :: Developers
Classifier: License :: OSI Approved :: MIT License
Classifier: Operating System :: OS Independent
